[{"timestamp":"2023-03-01T00:11:15.222Z","count":2,"uniques":2},{"timestamp":"2023-04-01T00:11:44.709Z","count":0,"uniques":0},{"timestamp":"2023-05-01T00:11:17.029Z","count":7,"uniques":1},{"timestamp":"2023-06-01T06:04:01.481Z","count":35,"uniques":3},{"timestamp":"2023-07-01T00:21:30.171Z","count":1,"uniques":1},{"timestamp":"2023-08-01T18:03:20.714Z","count":2,"uniques":2},{"timestamp":"2023-09-01T18:03:37.327Z","count":182,"uniques":2},{"timestamp":"2023-10-01T18:03:18.367Z","count":1,"uniques":1},{"timestamp":"2023-11-01T18:03:23.529Z","count":47,"uniques":2},{"timestamp":"2023-12-01T00:10:45.427Z","count":0,"uniques":0},{"timestamp":"2024-01-01T12:04:12.056Z","count":11,"uniques":1},{"timestamp":"2024-02-01T00:12:13.665Z","count":23,"uniques":1}]
